ticketlog/__init__.py
ticketlog/web_ui.py
ticketlog/htdocs/ticketlog.css
ticketlog/htdocs/ticketlog.js
ticketlog/locale/messages.pot
ticketlog/locale/de_DE/LC_MESSAGES/ticketlog.mo
ticketlog/locale/de_DE/LC_MESSAGES/ticketlog.po
TracTicketChangelog-1.2.0.dist-info/COPYING
TracTicketChangelog-1.2.0.dist-info/METADATA
TracTicketChangelog-1.2.0.dist-info/WHEEL
TracTicketChangelog-1.2.0.dist-info/entry_points.txt
TracTicketChangelog-1.2.0.dist-info/top_level.txt
TracTicketChangelog-1.2.0.dist-info/RECORD
