Metadata-Version: 2.1
Name: TracTicketChangelog
Version: 1.2.0
Summary: Show changelogs in trac ticket
Home-page: https://trac-hacks.org/wiki/TracTicketChangelogPlugin
Author: Richard Liao
Author-email: richard.liao.i@gmail.com
Maintainer: Ryan J Ollos
Maintainer-email: ryan.j.ollos@gmail.com
License: 3-Clause BSD
Keywords: trac plugin
Platform: UNKNOWN
Classifier: Framework :: Trac
Requires-Dist: Trac
